venusian/__init__.py
venusian/advice.py
venusian/compat.py
venusian-3.1.0.dist-info/LICENSE.txt
venusian-3.1.0.dist-info/METADATA
venusian-3.1.0.dist-info/WHEEL
venusian-3.1.0.dist-info/top_level.txt
venusian-3.1.0.dist-info/RECORD
