Metadata-Version: 2.1
Name: venusian
Version: 3.1.0
Summary: A library for deferring decorator actions
Home-page: https://pylonsproject.org/
Author: Chris McDonough, Agendaless Consulting
Author-email: pylons-devel@googlegroups.com
License: BSD-derived (Repoze)
Keywords: web wsgi zope
Classifier: Development Status :: 6 - Mature
Classifier: Intended Audience :: Developers
Classifier: Programming Language :: Python :: 3
Classifier: Programming Language :: Python :: 3.7
Classifier: Programming Language :: Python :: 3.8
Classifier: Programming Language :: Python :: 3.9
Classifier: Programming Language :: Python :: 3.10
Classifier: Programming Language :: Python :: 3.11
Classifier: Programming Language :: Python :: 3.12
Classifier: Programming Language :: Python :: Implementation :: CPython
Classifier: Programming Language :: Python :: Implementation :: PyPy
Classifier: License :: Repoze Public License
Requires-Python: >=3.7
License-File: LICENSE.txt
Provides-Extra: testing
Requires-Dist: pytest; extra == "testing"
Requires-Dist: pytest-cov; extra == "testing"
Requires-Dist: coverage; extra == "testing"
Provides-Extra: docs
Requires-Dist: Sphinx>=4.3.2; extra == "docs"
Requires-Dist: repoze.sphinx.autointerface; extra == "docs"
Requires-Dist: pylons-sphinx-themes; extra == "docs"
Requires-Dist: sphinx-copybutton; extra == "docs"
